{
  "documentVersion": "1.0",
  "jsonSchemaSemanticVersion": "1.0.0",
  "imports": [
    {
      "corpusPath": "_allImports.cdm.json"
    }
  ],
  "definitions": [
    {
      "entityName": "CustomerConsent",
      "extendsEntity": "ODIEntity",
      "exhibitsTraits": [
        {
          "traitReference": "is.ODI.equivalent.entity",
          "arguments": [
            {
              "name": "equivalentOf",
              "value": "urn://odi.org/v1-beta/entities/customer/CustomerConsent"
            }
          ]
        },
        {
          "traitReference": "is.ODI.logicalReference",
          "arguments": [
            {
              "name": "definedAt",
              "value": "urn://odi.org/v1-beta/entities/customer/"
            }
          ]
        },
        {
          "traitReference": "has.entitySchemaAbstractionLevel",
          "arguments": [
            {
              "name": "level",
              "value": "logical"
            }
          ]
        },
        {
          "traitReference": "is.CDM.entityVersion",
          "arguments": [
            {
              "name": "versionNumber",
              "value": "1.0"
            }
          ]
        }
      ],
      "hasAttributes": [
        {
          "explanation": "Associated Customer instance.",
          "entity": {
            "entityReference": "Customer",
            "appliedTraits": [
              {
                "traitReference": "is.identifiedBy",
                "arguments": [
                  "Customer/(resolvedAttributes)/idValue"
                ]
              }
            ]
          },
          "resolutionGuidance": {
            "entityByReference": {
              "allowReference": true,
              "foreignKeyAttribute": {
                "purpose": "hasA",
                "dataType": "entityId",
                "name": "id",
                "appliedTraits": [
                  "is.ODI.attribute.required"
                ],
                "isNullable": true
              }
            }
          },
          "appliedTraits": [
            {
              "traitReference": "is.ODI.equivalent.entityAttribute",
              "arguments": [
                {
                  "name": "equivalentOf",
                  "value": "urn://odi.org/v1-beta/entities/customer/customer"
                }
              ]
            }
          ],
          "name": "customer"
        },
        {
          "explanation": "Associated Consent Definition instance.",
          "entity": {
            "entityReference": "ConsentDefinition",
            "appliedTraits": [
              {
                "traitReference": "is.identifiedBy",
                "arguments": [
                  "ConsentDefinition/(resolvedAttributes)/idValue"
                ]
              }
            ]
          },
          "resolutionGuidance": {
            "entityByReference": {
              "allowReference": true,
              "foreignKeyAttribute": {
                "purpose": "hasA",
                "dataType": "entityId",
                "name": "id",
                "appliedTraits": [
                  "is.ODI.attribute.required"
                ],
                "isNullable": true
              }
            }
          },
          "appliedTraits": [
            {
              "traitReference": "is.ODI.equivalent.entityAttribute",
              "arguments": [
                {
                  "name": "equivalentOf",
                  "value": "urn://odi.org/v1-beta/entities/customer/consentDefinition"
                }
              ]
            }
          ],
          "name": "consentDefinition"
        },
        {
          "name": "effectiveDateTime",
          "purpose": "hasA",
          "dataType": "dateTimeOffset",
          "appliedTraits": [
            "is.ODI.attribute.required",
            {
              "traitReference": "is.ODI.equivalent.attribute",
              "arguments": [
                {
                  "name": "equivalentOf",
                  "value": "urn://odi.org/v1-beta/entities/customer/effectiveDateTime"
                }
              ]
            }
          ],
          "displayName": "Effective Date Time",
          "description": "Effective date-time of when a customer has granted or refused the consent statement."
        },
        {
          "name": "isConsentGranted",
          "purpose": "hasA",
          "dataType": "boolean",
          "appliedTraits": [
            "is.ODI.attribute.required",
            {
              "traitReference": "is.ODI.equivalent.attribute",
              "arguments": [
                {
                  "name": "equivalentOf",
                  "value": "urn://odi.org/v1-beta/entities/customer/isConsentGranted"
                }
              ]
            }
          ],
          "displayName": "Is Consent Granted",
          "description": "Boolean value, indicating if the customer has granted the consent statement."
        }
      ],
      "displayName": "Customer Consent",
      "description": "Records of customers' given consents on the consent statements."
    }
  ]
}