{
        "$schema": "http://json-schema.org/draft-04/schema#",
        "title": "Plotter configurator descriptor",
        "description": "This schema defines the properties of a plotter configuration file",

        "type": "object",

        "properties": {
                "description": { "$ref": "../common/1.json#/definitions/description" },
                "plotter": {"$ref": "../common/1.json#/definitions/reference"},
                "data": {"$ref": "../experiment/common.json#/definitions/parameter_set"},
                "schema_version": { "$ref": "../common/1.json#/definitions/version" }
        },
        "required": [
                "plotter",
                "data"
        ],
        "additionalProperties": false
}
